Metadata-Version: 2.1
Name: dasker
Version: 1.0.1
Summary: monadic dask client in separate process
Home-page: http://github.com/drorspei/dasker
Author: Dror Speiser
License: MIT
License-File: LICENSE
